dsconfig/__init__.py
dsconfig/configure.py
dsconfig/diff.py
dsconfig/dump.py
dsconfig/excel.py
dsconfig/filtering.py
dsconfig/formatting.py
dsconfig/json2tango.py
dsconfig/output.py
dsconfig/remove.py
dsconfig/tangodb.py
dsconfig/utils.py
dsconfig/validate.py
dsconfig/viewer.py
dsconfig/appending_dict/__init__.py
dsconfig/appending_dict/caseless.py
dsconfig/appending_dict/test_appendingdict.py
dsconfig/schema/dsconfig.json
dsconfig/schema/schema2.json
dsconfig-1.8.0.dist-info/LICENSE.txt
dsconfig-1.8.0.dist-info/METADATA
dsconfig-1.8.0.dist-info/WHEEL
dsconfig-1.8.0.dist-info/entry_points.txt
dsconfig-1.8.0.dist-info/top_level.txt
dsconfig-1.8.0.dist-info/RECORD
