Metadata-Version: 2.1
Name: dsconfig
Version: 1.8.0
Summary: Library and utilities for Tango device configuration.
Home-page: https://gitlab.com/MaxIV/lib-maxiv-dsconfig
Author: KITS
Author-email: kits-sw@maxiv.lu.se
License: GPLv3
Keywords: Tango
Platform: UNKNOWN
Requires-Python: >=2.7
License-File: LICENSE.txt
Requires-Dist: jsonpatch >=1.13
Requires-Dist: jsonschema
Requires-Dist: six
Requires-Dist: xlrd
Requires-Dist: pytango
Provides-Extra: tests
Requires-Dist: pytest ; extra == 'tests'
Requires-Dist: pytest-cov ; extra == 'tests'
Requires-Dist: Faker ; extra == 'tests'
Requires-Dist: mock ; extra == 'tests'
